flet_rive/__init__.py
flet_rive/rive.py
flet_rive-0.80.5.dist-info/licenses/LICENSE
flutter/flet_rive/analysis_options.yaml
flutter/flet_rive/pubspec.lock
flutter/flet_rive/pubspec.yaml
flutter/flet_rive/lib/flet_rive.dart
flutter/flet_rive/lib/src/extension.dart
flutter/flet_rive/lib/src/rive.dart
flet_rive-0.80.5.dist-info/METADATA
flet_rive-0.80.5.dist-info/WHEEL
flet_rive-0.80.5.dist-info/top_level.txt
flet_rive-0.80.5.dist-info/RECORD
